{
  "updatedAt": "2026-03-21 10:16 UTC",
  "stats": {
    "signals24h": 12,
    "topChain": "Solana",
    "avgRisk": 38.0,
    "criticalAlerts": 0
  },
  "audits": [
    {
      "token": "W",
      "chain": "solana",
      "level": "low",
      "score": 26,
      "finding": "Top10 holders: 17.9337%"
    },
    {
      "token": "PISSCOIN",
      "chain": "solana",
      "level": "medium",
      "score": 50,
      "finding": "Top10 holders: 22.8918%"
    },
    {
      "token": "balanced",
      "chain": "solana",
      "level": "low",
      "score": 26,
      "finding": "Top10 holders: 18.0218%"
    },
    {
      "token": "XCAT",
      "chain": "solana",
      "level": "low",
      "score": 26,
      "finding": "Top10 holders: 18.6495%"
    },
    {
      "token": "Pete",
      "chain": "solana",
      "level": "medium",
      "score": 50,
      "finding": "Top10 holders: 22.0474%"
    },
    {
      "token": "CIA",
      "chain": "solana",
      "level": "medium",
      "score": 50,
      "finding": "Top10 holders: 22.9734%"
    }
  ],
  "signals": [
    {
      "t": "09:42 UTC",
      "chain": "solana",
      "type": "Smart Money",
      "token": "W",
      "usd": "1,297",
      "wallets": 8,
      "riskLevel": "low",
      "finding": "Top10 holders: 17.9337%"
    },
    {
      "t": "01:21 UTC",
      "chain": "solana",
      "type": "Smart Money",
      "token": "PISSCOIN",
      "usd": "1,544",
      "wallets": 8,
      "riskLevel": "medium",
      "finding": "Top10 holders: 22.8918%"
    },
    {
      "t": "20:52 UTC",
      "chain": "solana",
      "type": "Smart Money",
      "token": "balanced",
      "usd": "1,277",
      "wallets": 9,
      "riskLevel": "low",
      "finding": "Top10 holders: 18.0218%"
    },
    {
      "t": "18:07 UTC",
      "chain": "solana",
      "type": "Smart Money",
      "token": "XCAT",
      "usd": "1,129",
      "wallets": 9,
      "riskLevel": "low",
      "finding": "Top10 holders: 18.6495%"
    },
    {
      "t": "17:14 UTC",
      "chain": "solana",
      "type": "Smart Money",
      "token": "Pete",
      "usd": "1,143",
      "wallets": 3,
      "riskLevel": "medium",
      "finding": "Top10 holders: 22.0474%"
    },
    {
      "t": "15:32 UTC",
      "chain": "solana",
      "type": "Smart Money",
      "token": "CIA",
      "usd": "1,315",
      "wallets": 4,
      "riskLevel": "medium",
      "finding": "Top10 holders: 22.9734%"
    },
    {
      "t": "14:18 UTC",
      "chain": "solana",
      "type": "Smart Money",
      "token": "Chuck",
      "usd": "2,556",
      "wallets": 10,
      "riskLevel": "low",
      "finding": "Top10 holders: 16.0998%"
    },
    {
      "t": "10:57 UTC",
      "chain": "solana",
      "type": "Smart Money",
      "token": "CHIBIELON",
      "usd": "1,128",
      "wallets": 3,
      "riskLevel": "medium",
      "finding": "Top10 holders: 25.8708%"
    },
    {
      "t": "06:00 UTC",
      "chain": "solana",
      "type": "Smart Money",
      "token": "Dryer",
      "usd": "1,750",
      "wallets": 6,
      "riskLevel": "medium",
      "finding": "Top10 holders: 20.8436%"
    },
    {
      "t": "05:59 UTC",
      "chain": "solana",
      "type": "Smart Money",
      "token": "Pixel",
      "usd": "1,006",
      "wallets": 7,
      "riskLevel": "medium",
      "finding": "Top10 holders: 25.6167%"
    },
    {
      "t": "05:44 UTC",
      "chain": "solana",
      "type": "Smart Money",
      "token": "Dryer",
      "usd": "1,062",
      "wallets": 4,
      "riskLevel": "medium",
      "finding": "Top10 holders: 20.8436%"
    },
    {
      "t": "23:50 UTC",
      "chain": "solana",
      "type": "Smart Money",
      "token": "LIBERTY",
      "usd": "1,132",
      "wallets": 3,
      "riskLevel": "medium",
      "finding": "Top10 holders: 26.4448%"
    }
  ]
}